{"template":"__react_static_root__/src/containers/artwork","sharedHashesByProp":{},"data":{"work":{"title":" Birth of the day","id":53,"category":"svirska-prints","categoryName":"Prints","thumbKey":"th-2008-228- Birth of the day, monotype printing, 47x75cm, 250$.jpg","imageKey":"2008-228- Birth of the day, monotype printing, 47x75cm, 250$.jpg","description":{"title":" Birth of the day","category":{"id":"svirska-prints","name":"Prints"},"technique":"Monotype printing","dimensions":"47 x 75 cm","price":"250$","year":"2008","available":true}}},"path":"svirska-prints/work/53"}
